[
  {
    "topology_preset": "saturated",
    "requested_active_edges": 86,
    "seeded_active_edges": 86,
    "adjacency_json": null,
    "population_size": 1000,
    "steps": 240,
    "seconds": 0.5526632230000814,
    "ticks_per_second": 434.260848219974,
    "agent_steps_per_second": 434260.84821997397,
    "mean_active_synapses": 86.00000762939453,
    "device": "cuda",
    "dtype": "torch.float32",
    "torch_compile_requested": false,
    "torch_compile_active": false,
    "compile_error": null,
    "cuda_memory_allocated_mb": 4.6162109375,
    "cuda_max_memory_allocated_mb": 8.82275390625,
    "accelerator_backend": "cuda"
  },
  {
    "topology_preset": "saturated",
    "requested_active_edges": 86,
    "seeded_active_edges": 86,
    "adjacency_json": null,
    "population_size": 10000,
    "steps": 240,
    "seconds": 0.58798432399999,
    "ticks_per_second": 408.17414717335913,
    "agent_steps_per_second": 4081741.4717335915,
    "mean_active_synapses": 86.0,
    "device": "cuda",
    "dtype": "torch.float32",
    "torch_compile_requested": false,
    "torch_compile_active": false,
    "compile_error": null,
    "cuda_memory_allocated_mb": 46.59375,
    "cuda_max_memory_allocated_mb": 89.59033203125,
    "accelerator_backend": "cuda"
  },
  {
    "topology_preset": "saturated",
    "requested_active_edges": 86,
    "seeded_active_edges": 86,
    "adjacency_json": null,
    "population_size": 50000,
    "steps": 240,
    "seconds": 2.6036204709998856,
    "ticks_per_second": 92.17933361379326,
    "agent_steps_per_second": 4608966.680689663,
    "mean_active_synapses": 86.0,
    "device": "cuda",
    "dtype": "torch.float32",
    "torch_compile_requested": false,
    "torch_compile_active": false,
    "compile_error": null,
    "cuda_memory_allocated_mb": 230.603515625,
    "cuda_max_memory_allocated_mb": 440.9501953125,
    "accelerator_backend": "cuda"
  },
  {
    "topology_preset": "saturated",
    "requested_active_edges": 86,
    "seeded_active_edges": 86,
    "adjacency_json": null,
    "population_size": 100000,
    "steps": 240,
    "seconds": 5.168220268000141,
    "ticks_per_second": 46.43764923991306,
    "agent_steps_per_second": 4643764.923991306,
    "mean_active_synapses": 86.0,
    "device": "cuda",
    "dtype": "torch.float32",
    "torch_compile_requested": false,
    "torch_compile_active": false,
    "compile_error": null,
    "cuda_memory_allocated_mb": 462.23291015625,
    "cuda_max_memory_allocated_mb": 883.83642578125,
    "accelerator_backend": "cuda"
  }
]
